mkreadme/__init__.py
mkreadme/__main__.py
mkreadme/static/template.yml
mkreadme/template.py
mkreadme-0.4.0.dist-info/entry_points.txt
mkreadme-0.4.0.dist-info/WHEEL
mkreadme-0.4.0.dist-info/METADATA
mkreadme-0.4.0.dist-info/RECORD
