Metadata-Version: 2.1
Name: mkreadme
Version: 0.4.0
Summary: A cli tool to interactively generate a README file
Home-page: https://pypi.org/project/mkreadme/
License: MIT
Keywords: cli,readme,mkreadme
Author: An Hoang
Author-email: anhoang31415@gmail.com
Requires-Python: >=3.8,<4
Classifier: License :: OSI Approved :: MIT License
Classifier: Operating System :: OS Independent
Classifier: Programming Language :: Python :: 3
Classifier: Programming Language :: Python :: 3.10
Classifier: Programming Language :: Python :: 3.8
Classifier: Programming Language :: Python :: 3.9
Requires-Dist: PyYAML (>=6.0,<7.0)
Requires-Dist: click (>=8.1.3,<9.0.0)
Requires-Dist: inquirer (>=2.10.0,<3.0.0)
Requires-Dist: pydantic (>=1.9.2,<2.0.0)
Project-URL: Repository, https://github.com/AnH0ang/mkreadme
